dcchbot/__init__.py
dcchbot/__main__.py
dcchbot/main.py
dcchbot-1.9.7.dist-info/licenses/LICENSE
dcchbot-1.9.7.dist-info/METADATA
dcchbot-1.9.7.dist-info/WHEEL
dcchbot-1.9.7.dist-info/entry_points.txt
dcchbot-1.9.7.dist-info/top_level.txt
dcchbot-1.9.7.dist-info/RECORD
