Metadata-Version: 2.4
Name: dcchbot
Version: 1.9.7
Summary: 一個簡單的中文 Discord 管理機器人，支援 GUI 按鈕封鎖/禁言/警告        
Author-email: I_am_from_taiwan <102109040j@gmail.com>
License: MIT
Requires-Python: >=3.8
License-File: LICENSE
Requires-Dist: discord.py>=2.3.0
Dynamic: license-file
